LICENSE
nonebot_plugin_bam/__init__.py
nonebot_plugin_bam/activity.py
nonebot_plugin_bam/bilibili/__init__.py
nonebot_plugin_bam/bilibili/activity.py
nonebot_plugin_bam/bilibili/api.py
nonebot_plugin_bam/bilibili/live1.py
nonebot_plugin_bam/bilibili/live2.py
nonebot_plugin_bam/bilibili/user.py
nonebot_plugin_bam/bilibili/wbi.py
nonebot_plugin_bam/common.py
nonebot_plugin_bam/config.py
nonebot_plugin_bam/database/__init__.py
nonebot_plugin_bam/database/db.py
nonebot_plugin_bam/database/helper.py
nonebot_plugin_bam/database/tables/__init__.py
nonebot_plugin_bam/database/tables/bilibili_user.py
nonebot_plugin_bam/database/tables/bilibili_user_status.py
nonebot_plugin_bam/database/tables/follow_link.py
nonebot_plugin_bam/database/tables/group.py
nonebot_plugin_bam/follow.py
nonebot_plugin_bam/group.py
nonebot_plugin_bam/tasks/__init__.py
nonebot_plugin_bam/tasks/activity_monitor.py
nonebot_plugin_bam/tasks/live_monitor.py
nonebot_plugin_bam/user.py
nonebot_plugin_bam-0.2.1.dist-info/LICENSE
nonebot_plugin_bam-0.2.1.dist-info/METADATA
nonebot_plugin_bam-0.2.1.dist-info/WHEEL
nonebot_plugin_bam-0.2.1.dist-info/RECORD
