Metadata-Version: 2.1
Name: nonebot-plugin-bam
Version: 0.2.1
Summary: Bilibili activity monitor plugin for nonebot
Home-page: https://github.com/7sDream/nonebot-plugin-bam
License: MIT
Keywords: nonebot,bilibili,qqbot
Author: 7sDream
Author-email: i@7sdre.am
Requires-Python: >=3.9,<4.0
Classifier: Development Status :: 3 - Alpha
Classifier: Environment :: Plugins
Classifier: License :: OSI Approved :: MIT License
Classifier: Operating System :: OS Independent
Classifier: Programming Language :: Python :: 3
Classifier: Programming Language :: Python :: 3.9
Classifier: Programming Language :: Python :: 3.10
Classifier: Programming Language :: Python :: 3.11
Classifier: Topic :: Software Development :: Libraries :: Python Modules
Requires-Dist: aiohttp[speedups] (>=3.8.4,<4.0.0)
Requires-Dist: nonebot-adapter-onebot (>=2.2.3,<3.0.0)
Requires-Dist: nonebot-plugin-apscheduler (>=0.3.0,<0.4.0)
Requires-Dist: nonebot2 (>=2.0.0,<3.0.0)
Requires-Dist: peewee (>=3.16.2,<4.0.0)
Requires-Dist: pydantic (>=1.10.9,<2.0.0)
Project-URL: Repository, https://github.com/7sDream/nonebot-plugin-bam
